collector/__init__.py
collector/admin.py
collector/apps.py
collector/constants.py
collector/forms.py
collector/models.py
collector/tasks.py
collector/urls.py
collector/views.py
collector/locale/pl_PL/LC_MESSAGES/django.mo
collector/locale/pl_PL/LC_MESSAGES/django.po
collector/management/commands/setupinfluxdb.py
collector/migrations/0001_initial.py
collector/migrations/__init__.py
collector/tests/__init__.py
collector/tests/test_admin.py
collector/tests/test_forms.py
collector/tests/test_models.py
collector/tests/test_tasks.py
collector/tests/test_views.py
collector/tests/utils.py
watcheye_collector-2.0.0.dist-info/LICENSE
watcheye_collector-2.0.0.dist-info/METADATA
watcheye_collector-2.0.0.dist-info/WHEEL
watcheye_collector-2.0.0.dist-info/top_level.txt
watcheye_collector-2.0.0.dist-info/RECORD
