Metadata-Version: 2.1
Name: watcheye-collector
Version: 2.0.0
Summary: A Django application to collect monitoring data samples through HTTP or SNMP GET interface.
Home-page: https://github.com/watcheye/watcheye-collector
Author: Andrzej Mateja
Author-email: mateja.and@gmail.com
License: UNKNOWN
Platform: UNKNOWN
Classifier: Development Status :: 5 - Production/Stable
Classifier: Environment :: Web Environment
Classifier: Framework :: Django
Classifier: Framework :: Django :: 2.0
Classifier: Framework :: Django :: 2.1
Classifier: Intended Audience :: Developers
Classifier: License :: OSI Approved :: GNU Lesser General Public License v3 or later (LGPLv3+)
Classifier: Operating System :: OS Independent
Classifier: Programming Language :: Python
Classifier: Programming Language :: Python :: 3.5
Classifier: Programming Language :: Python :: 3.6
Classifier: Topic :: Internet :: WWW/HTTP
Requires-Dist: celery[redis] (>=4.2.0)
Requires-Dist: django (>=2.0.0)
Requires-Dist: influxdb (>=5.2.0)
Requires-Dist: pyasn1
Requires-Dist: pysnmp
